{
    "name": "Blue Atlas Cedar",
    "climate": [
        "The Blue Atlas Cedar thrives best in temperate climates where temperatures are moderate.",
        "It can tolerate a range of conditions but does not fare well in extremely cold climates.",
        "This tree prefers climates that afford distinct seasonal variations for its growth cycles.",
        "While adaptable, it performs optimally in climates with cool, moist winters and hot summers."
    ],
    "sunlight": [
        "Blue Atlas Cedar requires full sun exposure to thrive, needing ample direct sunlight.",
        "The tree should be planted in a location where it will receive sunlight for most of the day.",
        "Insufficient sunlight can lead to poor growth and a less dense canopy in the Blue Atlas Cedar.",
        "Placing the tree in a shaded area is not recommended as it might affect its development."
    ],
    "watering": [
        "Water the Blue Atlas Cedar deeply but infrequently to encourage deep root growth.",
        "During periods of drought, the tree will need more frequent watering to prevent stress.",
        "Newly planted cedars will require regular watering until their root systems are established.",
        "Overwatering should be avoided as it can lead to root rot and other health issues in the tree."
    ],
    "soil": [
        "Blue Atlas Cedar prefers well-drained, loamy soil that retains some moisture but drains well.",
        "The soil should have a neutral to slightly acidic pH for optimal growth and tree health.",
        "Poorly drained or overly compacted soils are not suitable for planting Blue Atlas Cedar.",
        "Adding organic matter to the soil can improve its structure and nutrient content for the tree."
    ],
    "toxic": [],
    "extra_care_tip": [
        "Prune the Blue Atlas Cedar sparingly to maintain its natural form and prevent damage."
    ]
}