{
    "name": "Early Harvest Apple Tree",
    "climate": [
        "Early Harvest Apple Trees thrive in temperate climates with distinct seasons.",
        "These trees require a cold winter for proper dormancy and fruit production.",
        "It prefers climates where summers are warm but not excessively hot or humid.",
        "The tree is suitable for growing in USDA hardiness zones 3 through 8."
    ],
    "sunlight": [
        "Early Harvest Apple Trees need full sunlight to produce the best fruit yield.",
        "The tree should receive at least six to eight hours of direct sunlight each day.",
        "Inadequate sunlight can lead to poor fruit development and lower overall health.",
        "Planting in a spot that gets morning sunlight is especially beneficial."
    ],
    "watering": [
        "Water young trees thoroughly to encourage deep root systems and strong growth.",
        "During the growing season, ensure consistent moisture to avoid drought stress.",
        "However, excessive water can lead to root rot, so proper drainage is essential.",
        "Mature trees need less frequent watering but should not be completely dry."
    ],
    "soil": [
        "Early Harvest Apple Trees prefer well-drained loamy soil rich in organic matter.",
        "The ideal soil pH for these trees ranges from 6.0 to 7.0 for optimal growth.",
        "Heavy clay or sandy soils should be amended with organic matter and compost.",
        "Good drainage is crucial to prevent waterlogging and promote healthy roots."
    ],
    "toxic": [
        "Apple seeds contain cyanogenic compounds that can be toxic if ingested in large quantities."
    ],
    "extra_care_tip": [
        "Regular pruning helps maintain tree shape, sunlight penetration, and fruit quality.",
        "Remove any fallen fruit and debris around the tree to prevent disease and pests."
    ]
}