{
    "name": "Radish",
    "climate": ["Radishes thrive best in cool and mild climates where temperatures range from 10°C to 18°C, promoting healthy root development.", "In hot weather conditions, radishes may bolt and produce flowers instead of roots, leading to poor crop yield.", "Avoid planting radishes in tropical or very hot climates as it can stress the plants and affect growth quality.", "Radishes can withstand light frosts but prolonged exposure to severe cold can damage their growth."],
    "sunlight": ["Radishes generally require full sun, which means they need at least six hours of direct sunlight every day.", "In areas with very hot climates, radishes benefit from partial shade to prevent bolting and enhance growth.", "Too much shade will lead to longer and weaker roots, as sufficient sunlight is key for root development.", "Plant radishes in a location with optimal sunlight in spring and fall for the best results."],
    "watering": ["Radishes need consistent and regular watering to ensure they do not dry out, which could impede proper root formation.", "Water radishes deeply but less frequently to encourage the development of a robust root system.", "Over-watering can be detrimental, causing roots to become waterlogged and possibly rot if the soil remains too wet.", "Ensure soil is always evenly moist with good drainage to maintain balance between hydration and drying."],
    "soil": ["Radishes grow best in loose, well-drained soil with a pH ranging from 5.8 to 6.8, facilitating proper root growth.", "Compacted or rocky soils can hinder radish growth; therefore, soil should be tilled and free from obstructions.", "Add organic matter like compost to the soil to increase nutrient content and improve its structure.", "Sandy loam soils are ideal as they allow for easier root expansion and prevent soil compaction issues."],
    "toxic": [],
    "extra_care_tip": ["Radishes benefit from thinning to prevent overcrowding; seedlings should be thinned out once they reach a few inches tall.", "Watch out for pests like aphids and root maggots; regular inspection and proper pest management are essential.", "Harvest radishes promptly once they mature; leaving them in the ground too long can result in pithy or woody roots.", "For a continuous harvest, practice successive planting by sowing seeds every couple of weeks."]
}