{
    "name": "White Oak",
    "climate": [
        "White Oaks thrive in a temperate climate with distinct seasons.",
        "They prefer regions where summers are warm and winters are cold.",
        "These trees can tolerate a variety of temperatures, but not extreme heat.",
        "In natural conditions, they grow in areas with adequate rainfall year-round."
    ],
    "sunlight": [
        "White Oaks require full sunlight for optimal growth and health.",
        "They need at least 6 hours of direct sunlight for a strong structure.",
        "Although they can survive in partial shade, full sun is preferable.",
        "Position in a location where they receive unfiltered, bright sunlight."
    ],
    "watering": [
        "Young White Oaks need regular watering to establish a deep root system.",
        "Mature White Oaks are drought-tolerant but prefer consistent moisture.",
        "Water thoroughly, ensuring the soil remains moist but not waterlogged.",
        "An inch of water per week, including rainfall, is generally adequate."
    ],
    "soil": [
        "White Oaks prefer well-drained soil to prevent root rot and other issues.",
        "They thrive best in loamy soil rich in organic matter and nutrients.",
        "Acidic to neutral pH levels are ideal, but they are adaptable to variance.",
        "Avoid heavy clay soils as they can retain too much water in rainy seasons."
    ],
    "toxic": [],
    "extra_care_tip": [
        "Prune White Oaks during their dormant season to maintain shape and health.",
        "Regular mulching helps retain soil moisture and regulate temperature.",
        "Protect young oaks from deer and rodents that may cause bark damage.",
        "Monitor for pests like oak wilt and take action promptly if detected."
    ]
}